pg2elastic/__init__.py
pg2elastic/base.py
pg2elastic/constants.py
pg2elastic/exc.py
pg2elastic/helper.py
pg2elastic/node.py
pg2elastic/plugin.py
pg2elastic/querybuilder.py
pg2elastic/redisqueue.py
pg2elastic/search_client.py
pg2elastic/settings.py
pg2elastic/singleton.py
pg2elastic/sync.py
pg2elastic/transform.py
pg2elastic/trigger.py
pg2elastic/urls.py
pg2elastic/utils.py
pg2elastic/view.py
pg2elastic/pgoutput/__init__.py
pg2elastic/pgoutput/decoder.py
pg2elastic/pgoutput/formatter.py
pg2elastic/pgoutput/reader.py
pg2elastic/pgoutput/types.py
pg2elastic-0.3.6.data/scripts/bootstrap
pg2elastic-0.3.6.data/scripts/pg2elastic
pg2elastic-0.3.6.dist-info/LICENSE
pg2elastic-0.3.6.dist-info/METADATA
pg2elastic-0.3.6.dist-info/WHEEL
pg2elastic-0.3.6.dist-info/top_level.txt
pg2elastic-0.3.6.dist-info/RECORD
